{"front-end_css_index.md":"f581f58c","front-end_html_index.md":"06aa2104","front-end_javascript_index.md":"bc20d5ab","front-end_react_react-api1.md":"39364280","front-end_react_react-api2.md":"4f292b2c","front-end_react_react-api3.md":"aa4d84ef","front-end_react_react-api4.md":"8edd49a3","front-end_react_useredux.md":"3b11a630","front-end_typescript_ts-study1.md":"a37d72de","front-end_typescript_ts-study2.md":"f8bde5ec","front-end_typescript_ts-study3.md":"6fa51a2f","front-end_typescript_ts-study4.md":"2f105228","front-end_typescript_ts-study5.md":"e7d427ea","index.md":"76fa6b09","other_github_synctogitee.md":"a1046943","other_leetcode_leetcode1.md":"ab672f60","tools_packetcapture.md":"1a6ce4d9"}
